get_papers_list/__init__.py
get_papers_list/get_papers.py
get_papers_list/pubmed_api.py
get_papers_list-0.1.4.dist-info/entry_points.txt
get_papers_list-0.1.4.dist-info/METADATA
get_papers_list-0.1.4.dist-info/WHEEL
get_papers_list-0.1.4.dist-info/RECORD
